{"_id":{"$oid":"5e56a0eed9ee3ddab5493079"},"id":{"$numberInt":"1"},"password":"pbkdf2_sha256$150000$IlIXT0N0ucer$TnuZLDSFsJ+GEwZjC+znoUk/7XlnRa9imgP5UG4KdyU=","last_login":{"$date":{"$numberLong":"1583417307226"}},"is_superuser":true,"username":"tomillo","first_name":"","last_name":"","email":"","is_staff":true,"is_active":true,"date_joined":{"$date":{"$numberLong":"1582735598641"}}}
{"_id":{"$oid":"5e5e7d8a3b661aee65a7a92b"},"id":{"$numberInt":"2"},"password":"pbkdf2_sha256$150000$pebQnb4qvaDC$suB0bbgrCf/HopJAPJZWhs0OHaeylSrpLqtr0GH3/NA=","last_login":{"$date":{"$numberLong":"1583250844946"}},"is_superuser":false,"username":"Franco123","first_name":"Francisco","last_name":"España","email":"gaviotacasta206@gmail.com","is_staff":false,"is_active":true,"date_joined":{"$date":{"$numberLong":"1583250826729"}}}
{"_id":{"$oid":"5e5f867edd2e6a304b7ee9eb"},"id":{"$numberInt":"3"},"password":"pbkdf2_sha256$150000$iG0LG9heAtWg$OQ4hwq3raXw7NkqS0HgifxvTaI8vrk8IEikQvIpUS/Q=","last_login":{"$date":{"$numberLong":"1583422708241"}},"is_superuser":false,"username":"VillaTomillo123","first_name":"Tomillo","last_name":"Madrid","email":"villaTomillo@gmail.com","is_staff":false,"is_active":true,"date_joined":{"$date":{"$numberLong":"1583318653750"}}}
